AUTHORS
LICENSE
MANIFEST.in
README.rst
setup.py
altuser/__init__.py
altuser/admin.py
altuser/forms.py
altuser/models.py
altuser/tests.py
altuser/views.py
altuser/locale/it/LC_MESSAGES/django.mo
altuser/locale/it/LC_MESSAGES/django.po
altuser/templates/altuser/mail_account_confirmation_succeded.html
altuser/templates/altuser/mail_account_request.html
altuser/templates/altuser/mail_follows_confirmation_succeded.html
altuser/templates/altuser/mail_follows_request.html
django_altuser.egg-info/PKG-INFO
django_altuser.egg-info/SOURCES.txt
django_altuser.egg-info/dependency_links.txt
django_altuser.egg-info/top_level.txt