Metadata-Version: 1.1
Name: django-altuser
Version: 0.9.3
Summary: Alternates user models for use with django >= 1.5
Home-page: http://v.licheni.net/drc/django-altuser.git
Author: Davide Riccardo Caliendo
Author-email: davide.licheni.net
License: GPLv3 License
Platform: UNKNOWN
Classifier: Environment :: Web Environment
Classifier: Framework :: Django
Classifier: Intended Audience :: Developers
Classifier: License :: OSI Approved :: GNU General Public License v3 (GPLv3)
Classifier: Operating System :: OS Independent
Classifier: Programming Language :: Python
Classifier: Programming Language :: Python :: 2.6
Classifier: Programming Language :: Python :: 2.7
Classifier: Topic :: Internet :: WWW/HTTP
Classifier: Topic :: Internet :: WWW/HTTP :: Dynamic Content
